dnc_crypto/__init__.py
dnc_crypto/core.py
dnc_crypto/exceptions.py
dnc_crypto/key_manager.py
dnc_crypto-1.0.9.dist-info/LICENSE
dnc_crypto-1.0.9.dist-info/METADATA
dnc_crypto-1.0.9.dist-info/WHEEL
dnc_crypto-1.0.9.dist-info/top_level.txt
dnc_crypto-1.0.9.dist-info/RECORD
