Metadata-Version: 2.1
Name: dnc_crypto
Version: 1.0.9
Summary: A high-performance, industrial-grade cipher with optional GPU acceleration.
Author: Mohammadmoein Pisoude
Author-email: mmoeinp3@gmail.com
Classifier: Programming Language :: Python :: 3
Classifier: License :: OSI Approved :: MIT License
Classifier: Operating System :: OS Independent
Classifier: Topic :: Security :: Cryptography
Requires-Python: >=3.7
License-File: LICENSE
Requires-Dist: numpy
Requires-Dist: cryptography
Requires-Dist: networkx
Requires-Dist: pynacl
Provides-Extra: gpu
Requires-Dist: cupy-cuda12x ; extra == 'gpu'
